supervisorex/__init__.py
supervisorex/cli.py
supervisorex-1.1.1.dist-info/licenses/LICENSE
supervisorex-1.1.1.dist-info/METADATA
supervisorex-1.1.1.dist-info/WHEEL
supervisorex-1.1.1.dist-info/entry_points.txt
supervisorex-1.1.1.dist-info/top_level.txt
supervisorex-1.1.1.dist-info/RECORD
