Metadata-Version: 2.4
Name: supervisorex
Version: 1.1.1
Summary: Simple CLI to create supervisor processes easily
Home-page: https://github.com/yuvrajmodz/supervisorex
Author: @NacDevs
Author-email: yuvrajmodz@gmail.com
Classifier: Programming Language :: Python :: 3
Classifier: License :: OSI Approved :: MIT License
Classifier: Operating System :: POSIX :: Linux
Requires-Python: >=3.8
License-File: LICENSE
Dynamic: author
Dynamic: author-email
Dynamic: classifier
Dynamic: description
Dynamic: description-content-type
Dynamic: home-page
Dynamic: license-file
Dynamic: requires-python
Dynamic: summary
